ola_cli/__init__.py
ola_cli/backup.py
ola_cli/cli.py
ola_ai-1.0.2.dist-info/METADATA
ola_ai-1.0.2.dist-info/WHEEL
ola_ai-1.0.2.dist-info/entry_points.txt
ola_ai-1.0.2.dist-info/top_level.txt
ola_ai-1.0.2.dist-info/RECORD
