Metadata-Version: 2.1
Name: ola-ai
Version: 1.0.2
Requires-Dist: Click
Requires-Dist: PyYAML
Requires-Dist: openai
Requires-Dist: python-dotenv
